ServexTools/Enumerable.py
ServexTools/EscribirLog.py
ServexTools/GetTime.py
ServexTools/Limiter.py
ServexTools/MTRequest.py
ServexTools/Necesario.py
ServexTools/ReplicaDb.py
ServexTools/Table.py
ServexTools/TablePV.py
ServexTools/Tools.py
ServexTools/__init__.py
ServexTools/conexion.py
ServexTools/socket_manager.py
servextools-0.1.54.dist-info/licenses/LICENSE
servextools-0.1.54.dist-info/METADATA
servextools-0.1.54.dist-info/WHEEL
servextools-0.1.54.dist-info/top_level.txt
servextools-0.1.54.dist-info/RECORD
