Metadata-Version: 2.4
Name: servextools
Version: 0.1.54
Summary: Herramientas para Servextex
Home-page: https://github.com/Servextex/ServexTools
Author: Servextex
Author-email: Servextex <info@servextex.com.do>
License: MIT License
Requires-Python: >=3.8
License-File: LICENSE
Requires-Dist: flask
Requires-Dist: pymongo
Requires-Dist: pytz
Requires-Dist: PyJWT
Requires-Dist: httpx
Requires-Dist: gevent
Requires-Dist: flask-socketio
Requires-Dist: tqdm
Requires-Dist: polars-lts-cpu
Requires-Dist: numpy
Dynamic: author
Dynamic: home-page
Dynamic: license-file
Dynamic: requires-python
